{"cameraMode":{"drawMode":0,"name":"Shaded","section":"Shading Mode"},"sceneLighting":false,"audioPlay":false,"sceneViewState":{"m_AlwaysRefresh":false,"showFog":true,"showSkybox":false,"showFlares":true,"showImageEffects":true,"showParticleSystems":true,"showVisualEffectGraphs":true,"m_FxEnabled":true},"in2DMode":false,"pivot":{"x":-0.7160054445266724,"y":-0.8610997200012207,"z":-1.0113893747329713},"rotation":{"x":-0.07468091696500778,"y":0.9201213717460632,"z":-0.31795284152030947,"w":-0.2161184698343277},"size":1.0772156715393067,"orthographic":false}